snakemake_testing/__init__.py
snakemake_testing/runner.py
snakemake_testing/version.py
snakemake_testing-0.0.2.dist-info/LICENSE
snakemake_testing-0.0.2.dist-info/METADATA
snakemake_testing-0.0.2.dist-info/WHEEL
snakemake_testing-0.0.2.dist-info/RECORD
